mageic_common/__init__.py
mageic_common/enum/__init__.py
mageic_common/enum/apps/__init__.py
mageic_common/enum/apps/stages.py
mageic_common/enum/apps/type.py
mageic_common/enum/models/__init__.py
mageic_common/enum/models/adapter.py
mageic_common/enum/models/base.py
mageic_common/enum/models/controlnet.py
mageic_common/enum/models/face_analysis.py
mageic_common/enum/models/scheduler.py
mageic_common/enum/models/upscaler.py
mageic_common/enum/moderation/__init__.py
mageic_common/enum/moderation/concept.py
mageic_common/models/__init__.py
mageic_common/models/backend/__init__.py
mageic_common/models/backend/run.py
mageic_common/models/backend/test.py
mageic_common/models/io/__init__.py
mageic_common/models/io/adapter.py
mageic_common/models/io/app.py
mageic_common/models/io/base.py
mageic_common/models/io/controlnet.py
mageic_common/models/io/moderation.py
mageic_common-0.4.0.dist-info/LICENSE.txt
mageic_common-0.4.0.dist-info/METADATA
mageic_common-0.4.0.dist-info/WHEEL
mageic_common-0.4.0.dist-info/top_level.txt
mageic_common-0.4.0.dist-info/RECORD
