Metadata-Version: 2.1
Name: mageic-common
Version: 0.4.0
Author: Gregory D. Hunkins
Author-email: greg@ollano.com
License: Copyright (C) (2024) Ollano, Inc. - All Rights Reserved
License-File: LICENSE.txt
Requires-Dist: numpy
Requires-Dist: Pillow
Requires-Dist: pydantic >=2.0.0
